alphacoders_downloader/__init__.py
alphacoders_downloader/__main__.py
alphacoders_downloader/alphacoders_downloader.py
alphacoders_downloader/exceptions.py
alphacoders_downloader/util/__init__.py
alphacoders_downloader/util/arguments_builder.py
alphacoders_downloader/util/cursor.py
alphacoders_downloader/util/progress_bar.py
alphacoders_downloader/util/spinner.py
alphacoders_downloader/util/utils.py
AlphacodersDownloader-0.1.4.3.dist-info/LICENSE
AlphacodersDownloader-0.1.4.3.dist-info/METADATA
AlphacodersDownloader-0.1.4.3.dist-info/WHEEL
AlphacodersDownloader-0.1.4.3.dist-info/entry_points.txt
AlphacodersDownloader-0.1.4.3.dist-info/top_level.txt
AlphacodersDownloader-0.1.4.3.dist-info/RECORD
