Metadata-Version: 2.1
Name: AlphacodersDownloader
Version: 0.1.4.3
Summary: A script for download wallpapers on https://alphacoders.com written in Python.
Home-page: https://github.com/Asthowen/AlphacodersDownloader
Author: Asthowen
Author-email: contact@asthowen.fr
Maintainer: Asthowen
Maintainer-email: contact@asthowen.fr
License: GNU v3.0
Project-URL: GitHub: issues, https://github.com/Asthowen/AlphacodersDownloader/issues
Project-URL: GitHub: repo, https://github.com/Asthowen/AlphacodersDownloader
Classifier: Development Status :: 5 - Production/Stable
Classifier: Framework :: AsyncIO
Classifier: Intended Audience :: Developers
Classifier: License :: OSI Approved :: GNU General Public License v3 (GPLv3)
Classifier: Operating System :: POSIX
Classifier: Operating System :: MacOS :: MacOS X
Classifier: Operating System :: Microsoft :: Windows
Classifier: Programming Language :: Python
Classifier: Programming Language :: Python :: 3
Classifier: Programming Language :: Python :: 3.7
Classifier: Programming Language :: Python :: 3.8
Classifier: Programming Language :: Python :: 3.9
Classifier: Programming Language :: Python :: 3.10
Classifier: Topic :: Internet :: WWW/HTTP
Requires-Python: >= 3.6
License-File: LICENSE
Requires-Dist: aiohttp
Requires-Dist: aiofiles
Requires-Dist: setproctitle
Requires-Dist: beautifulsoup4
